{"v":4,"entries":{"introduksjon--docs":{"id":"introduksjon--docs","title":"Introduksjon","name":"Docs","importPath":"./stories/documentation/introduksjon.mdx","storiesImports":[],"type":"docs","tags":["unattached-mdx","docs"]},"oppsett--docs":{"id":"oppsett--docs","title":"Oppsett","name":"Docs","importPath":"./stories/documentation/oppsett.mdx","storiesImports":[],"type":"docs","tags":["unattached-mdx","docs"]},"bidra--docs":{"id":"bidra--docs","title":"Bidra","name":"Docs","importPath":"./stories/documentation/bidra.mdx","storiesImports":[],"type":"docs","tags":["unattached-mdx","docs"]},"komponenter-typografi-heading--docs":{"id":"komponenter-typografi-heading--docs","title":"Komponenter/Typografi/Heading","name":"Docs","importPath":"./stories/components/Typography/Heading/Heading.mdx","storiesImports":["./stories/components/Typography/Heading/Heading.stories.tsx"],"type":"docs","tags":["attached-mdx","docs"]},"komponenter-typografi-text--docs":{"id":"komponenter-typografi-text--docs","title":"Komponenter/Typografi/Text","name":"Docs","importPath":"./stories/components/Typography/Text/Text.mdx","storiesImports":["./stories/components/Typography/Text/Text.stories.tsx"],"type":"docs","tags":["attached-mdx","docs"]},"design-tokens--docs":{"id":"design-tokens--docs","title":"Design tokens","name":"Docs","importPath":"./stories/design-tokens/design-tokens.mdx","storiesImports":[],"type":"docs","tags":["unattached-mdx","docs"]},"komponenter-knapper--docs":{"id":"komponenter-knapper--docs","title":"Komponenter/Knapper","name":"Docs","importPath":"./stories/components/Button/Button.stories.tsx","type":"docs","tags":["docs","autodocs"],"storiesImports":[]},"komponenter-knapper--default":{"id":"komponenter-knapper--default","title":"Komponenter/Knapper","name":"Knapp","importPath":"./stories/components/Button/Button.stories.tsx","tags":["story"],"type":"story"},"komponenter-typografi-heading--heading":{"id":"komponenter-typografi-heading--heading","title":"Komponenter/Typografi/Heading","name":"Heading","importPath":"./stories/components/Typography/Heading/Heading.stories.tsx","tags":["story"],"type":"story"},"komponenter-typografi-text--text":{"id":"komponenter-typografi-text--text","title":"Komponenter/Typografi/Text","name":"Text","importPath":"./stories/components/Typography/Text/Text.stories.tsx","tags":["story"],"type":"story"}}}
